tartare/__init__.py
tartare/py.typed
tartare-0.0.1.dist-info/LICENSE
tartare-0.0.1.dist-info/METADATA
tartare-0.0.1.dist-info/WHEEL
tartare-0.0.1.dist-info/top_level.txt
tartare-0.0.1.dist-info/RECORD
