Metadata-Version: 2.1
Name: tartare
Version: 0.0.1
Summary: Data filters
Author-email: Allen Institute for Artificial Intelligence <contact@allenai.org>
License: Apache-2.0
Classifier: Development Status :: 3 - Alpha
Classifier: Typing :: Typed
Classifier: Programming Language :: Python :: Implementation :: CPython
Requires-Python: >=3.8
License-File: LICENSE
Requires-Dist: numpy
Provides-Extra: all
Requires-Dist: tartare[dev] ; extra == 'all'
Provides-Extra: dev
Requires-Dist: black >=22.6.0 ; extra == 'dev'
Requires-Dist: isort >=5.10.1 ; extra == 'dev'
Requires-Dist: mypy >=0.971 ; extra == 'dev'
Requires-Dist: pytest >=5.2 ; extra == 'dev'
Requires-Dist: ipython >=8.4.0 ; extra == 'dev'
Requires-Dist: autopep8 >=1.7.0 ; extra == 'dev'
Requires-Dist: flake8 >=5.0 ; extra == 'dev'
Requires-Dist: ipdb >=0.13.0 ; extra == 'dev'
Requires-Dist: flake8-pyi >=22.8.1 ; extra == 'dev'
Requires-Dist: Flake8-pyproject >=1.1.0 ; extra == 'dev'
